__init__.py
manage.py
dvt/__init__.py
dvt/asgi.py
dvt/settings.py
dvt/urls.py
dvt/wsgi.py
video_transcoding/__init__.py
video_transcoding/admin.py
video_transcoding/apps.py
video_transcoding/celery.py
video_transcoding/defaults.py
video_transcoding/forms.py
video_transcoding/helpers.py
video_transcoding/models.py
video_transcoding/signals.py
video_transcoding/tasks.py
video_transcoding/utils.py
video_transcoding/locale/ru/LC_MESSAGES/django.po
video_transcoding/migrations/0001_initial.py
video_transcoding/migrations/0002_auto_20200226_0919.py
video_transcoding/migrations/0003_auto_20200525_1130.py
video_transcoding/migrations/0004_audioprofile_audiotrack_preset_audioprofiletracks_and_more.py
video_transcoding/migrations/0005_video_metadata.py
video_transcoding/migrations/__init__.py
video_transcoding/tests/__init__.py
video_transcoding/tests/base.py
video_transcoding/tests/test_models.py
video_transcoding/tests/test_tasks.py
video_transcoding/tests/test_transcoding.py
video_transcoding/transcoding/__init__.py
video_transcoding/transcoding/codecs.py
video_transcoding/transcoding/metadata.py
video_transcoding/transcoding/profiles.py
video_transcoding/transcoding/transcoder.py
django_video_transcoding-1.0.0.dist-info/LICENSE
django_video_transcoding-1.0.0.dist-info/METADATA
django_video_transcoding-1.0.0.dist-info/WHEEL
django_video_transcoding-1.0.0.dist-info/top_level.txt
django_video_transcoding-1.0.0.dist-info/RECORD
