Metadata-Version: 2.1
Name: django_video_transcoding
Version: 1.0.0
Summary: Simple video transcoding application for Django framework
Author-email: Sergey Tikhonov <zimbler@gmail.com>
License: MIT
Project-URL: homepage, https://github.com/just-work/django-video-transcoding
Project-URL: documentation, https://django-video-transcoding.readthedocs.io/en/latest/
Project-URL: repository, https://github.com/just-work/django-video-transcoding.git
Project-URL: issues, https://github.com/just-work/django-video-transcoding/issues
Keywords: django,video,media,transcoding,processing
Classifier: Development Status :: 4 - Beta
Classifier: Environment :: Console
Classifier: Framework :: Django :: 3.2
Classifier: Framework :: Django :: 4.0
Classifier: Framework :: Django :: 4.1
Classifier: Framework :: Django :: 4.2
Classifier: Framework :: Django :: 5.0
Classifier: Operating System :: POSIX
Classifier: Programming Language :: Python :: 3.8
Classifier: Programming Language :: Python :: 3.9
Classifier: Programming Language :: Python :: 3.10
Classifier: Programming Language :: Python :: 3.11
Classifier: Programming Language :: Python :: 3.12
Classifier: Topic :: Multimedia :: Video :: Conversion
License-File: LICENSE
Requires-Dist: Django <5.1,>=3.2
Requires-Dist: django-model-utils <4.6.0,>=4.2.0
Requires-Dist: Celery <5.5.0,>=5.0.5
Requires-Dist: kombu <5.4.0,>=5.0.2
Requires-Dist: billiard <4.3.0,>=3.6.4.0
Requires-Dist: requests <2.33,>=2.25
Requires-Dist: pymediainfo <6.2,>=5.0.3
Requires-Dist: fffw ~=5.0.0
